{
  "better-comments.highlightPlainText": true,
  "better-comments.tags": [
    {
      "backgroundColor": "transparent",
      "bold": false,
      "color": "#FF2D00",
      "italic": false,
      "strikethrough": false,
      "tag": "!",
      "underline": false
    },
    {
      "backgroundColor": "transparent",
      "bold": false,
      "color": "#FF7150",
      "italic": true,
      "strikethrough": false,
      "tag": "-b",
      "underline": false
    },
    {
      "backgroundColor": "transparent",
      "bold": false,
      "color": "#D2FF63",
      "italic": true,
      "strikethrough": false,
      "tag": "-i",
      "underline": false
    },
    {
      "backgroundColor": "transparent",
      "bold": false,
      "color": "#ACFF69",
      "italic": false,
      "strikethrough": false,
      "tag": "-u",
      "underline": true
    },
    {
      "backgroundColor": "transparent",
      "bold": false,
      "color": "#3498DB",
      "italic": false,
      "strikethrough": false,
      "tag": "?",
      "underline": false
    },
    {
      "backgroundColor": "transparent",
      "bold": false,
      "color": "#474747",
      "italic": false,
      "strikethrough": true,
      "tag": "//",
      "underline": false
    },
    {
      "backgroundColor": "transparent",
      "bold": false,
      "color": "#FF8C00",
      "italic": false,
      "strikethrough": false,
      "tag": "todo",
      "underline": false
    },
    {
      "backgroundColor": "transparent",
      "bold": false,
      "color": "#F6A6F1",
      "italic": false,
      "strikethrough": false,
      "tag": "*",
      "underline": false
    },
    {
      "backgroundColor": "transparent",
      "bold": false,
      "color": "#F5B57B",
      "italic": false,
      "strikethrough": false,
      "tag": "-n",
      "underline": false
    }
  ],
  "bracket-pair-colorizer-2.depreciation-notice": false,
  "codestream.serverUrl": "https://api.codestream.com",
  "editor.accessibilitySupport": "off",
  "editor.fontFamily": "Fira Code",
  "editor.fontLigatures": true,
  "editor.fontSize": 19,
  "editor.inlineSuggest.enabled": true,
  "editor.occurrencesHighlight": "off",
  "editor.quickSuggestions": {
    "comments": "off",
    "other": "on",
    "strings": "off"
  },
  "editor.renderLineHighlight": "gutter",
  "editor.selectionHighlight": false,
  "explorer.confirmDelete": false,
  "git.terminalAuthentication": false,
  "github.gitAuthentication": false,
  "indentRainbow.indicatorStyle": "light",
  "indentRainbow.lightIndicatorStyleLineWidth": 5,
  "powermode.combo.counterSize": 2,
  "powermode.combo.timeout": 5,
  "powermode.enabled": false,
  "powermode.explosions.customExplosions": [],
  "powermode.explosions.enabled": true,
  "powermode.presets": "magic",
  "powermode.shake.intensity": 0,
  "tabnine.experimentalAutoImports": true,
  "terminal.integrated.env.osx": {
    "FIG_NEW_SESSION": "1"
  },
  "terminal.integrated.fontFamily": "'MesloLGS NF'",
  "terminal.integrated.fontWeight": "normal",
  "vim.commandLineModeKeyBindings": [],
  "workbench.colorCustomizations": {
    "[Material Theme]": {},
    "activityBar.activeBackground": "#ab307e",
    "activityBar.background": "#ab307e",
    "activityBar.foreground": "#e7e7e7",
    "activityBar.inactiveForeground": "#e7e7e799",
    "activityBarBadge.background": "#25320e",
    "activityBarBadge.foreground": "#e7e7e7",
    "commandCenter.border": "#e7e7e799",
    "sash.hoverBorder": "#ab307e",
    "statusBar.background": "#832561",
    "statusBar.foreground": "#e7e7e7",
    "statusBarItem.hoverBackground": "#ab307e",
    "statusBarItem.remoteBackground": "#832561",
    "statusBarItem.remoteForeground": "#e7e7e7",
    "titleBar.activeBackground": "#832561",
    "titleBar.activeForeground": "#e7e7e7",
    "titleBar.inactiveBackground": "#83256199",
    "titleBar.inactiveForeground": "#e7e7e799"
  },
  "workbench.iconTheme": "material-icon-theme",
  "editor.guides.bracketPairs": true,
  "rust-analyzer.hover.documentation.enable": false,
  "rust-analyzer.hover.documentation.keywords.enable": false,
  "rust-analyzer.hover.actions.run.enable": false,
  "rust-analyzer.hover.links.enable": false,
  "rust-analyzer.hover.actions.implementations.enable": false,
  "rust-analyzer.hover.actions.enable": false,
  "rust-analyzer.inlayHints.chainingHints.enable": false,
  "rust-analyzer.inlayHints.closingBraceHints.enable": false,
  "rust-analyzer.inlayHints.parameterHints.enable": false,
  "rust-analyzer.inlayHints.typeHints.enable": false,
  "rust-analyzer.inlayHints.renderColons": false,
  "explorer.confirmDragAndDrop": false,
  "rust-analyzer.cargo.target": "wasm32-unknown-unknown",
  "[python]": {
    "editor.formatOnType": true
  },
  "files.autoSave": "afterDelay",
  "terminal.integrated.enableMultiLinePasteWarning": false,
  "go.toolsManagement.autoUpdate": true,
  "liveServer.settings.donotShowInfoMsg": true,
  "editor.unicodeHighlight.ambiguousCharacters": false,
  "editor.defaultFormatter": "rust-lang.rust-analyzer",
  "editor.formatOnSave": true,
  "vsicons.dontShowNewVersionMessage": true,
  "workbench.colorTheme": "Dracula Soft",
  "code-runner.executorMap": {
    "javascript": "node",
    "java": "cd $dir && javac $fileName && java $fileNameWithoutExt",
    "c": "cd $dir && gcc $fileName -o $fileNameWithoutExt && $dir$fileNameWithoutExt",
    "zig": "zig run",
    "cpp": "cd $dir && g++ $fileName -o $fileNameWithoutExt && $dir$fileNameWithoutExt",
    "objective-c": "cd $dir && gcc -framework Cocoa $fileName -o $fileNameWithoutExt && $dir$fileNameWithoutExt",
    "php": "php",
    "python": "python3 -u",
    "perl": "perl",
    "perl6": "perl6",
    "ruby": "ruby",
    "go": "go run",
    "lua": "lua",
    "groovy": "groovy",
    "powershell": "powershell -ExecutionPolicy ByPass -File",
    "bat": "cmd /c",
    "shellscript": "bash",
    "fsharp": "fsi",
    "csharp": "scriptcs",
    "vbscript": "cscript //Nologo",
    "typescript": "ts-node",
    "coffeescript": "coffee",
    "scala": "scala",
    "swift": "swift",
    "julia": "julia",
    "crystal": "crystal",
    "ocaml": "ocaml",
    "r": "Rscript",
    "applescript": "osascript",
    "clojure": "lein exec",
    "haxe": "haxe --cwd $dirWithoutTrailingSlash --run $fileNameWithoutExt",
    "rust": "cd $dir && rustc $fileName && $dir$fileNameWithoutExt",
    "racket": "racket",
    "scheme": "csi -script",
    "ahk": "autohotkey",
    "autoit": "autoit3",
    "dart": "dart",
    "pascal": "cd $dir && fpc $fileName && $dir$fileNameWithoutExt",
    "d": "cd $dir && dmd $fileName && $dir$fileNameWithoutExt",
    "haskell": "runghc",
    "nim": "nim compile --verbosity:0 --hints:off --run",
    "lisp": "sbcl --script",
    "kit": "kitc --run",
    "v": "v run",
    "sass": "sass --style expanded",
    "scss": "scss --style expanded",
    "less": "cd $dir && lessc $fileName $fileNameWithoutExt.css",
    "FortranFreeForm": "cd $dir && gfortran $fileName -o $fileNameWithoutExt && $dir$fileNameWithoutExt",
    "fortran-modern": "cd $dir && gfortran $fileName -o $fileNameWithoutExt && $dir$fileNameWithoutExt",
    "fortran_fixed-form": "cd $dir && gfortran $fileName -o $fileNameWithoutExt && $dir$fileNameWithoutExt",
    "fortran": "cd $dir && gfortran $fileName -o $fileNameWithoutExt && $dir$fileNameWithoutExt",
    "sml": "cd $dir && sml $fileName",
    "mojo": "mojo run",
    "erlang": "escript",
    "spwn": "spwn build",
    "pkl": "cd $dir && pkl eval -f yaml $fileName -o $fileNameWithoutExt.yaml",
    "gleam": "gleam run -m $fileNameWithoutExt"
  },
  "lldb.suppressUpdateNotifications": true,
  "codeium.enableConfig": {
    "*": true,
    "rust": false
  },
  "codeium.enableCodeLens": "hide_x",
  "solidity.telemetry": false
}
